README.rst
blink.py
setup.py
blink.egg-info/PKG-INFO
blink.egg-info/SOURCES.txt
blink.egg-info/dependency_links.txt
blink.egg-info/requires.txt
blink.egg-info/top_level.txt